scru64/__init__.py
scru64/counter_mode.py
scru64-1.0.2.dist-info/LICENSE
scru64-1.0.2.dist-info/METADATA
scru64-1.0.2.dist-info/WHEEL
scru64-1.0.2.dist-info/RECORD
